pistonapi/__init__.py
pistonapi/exceptions.py
pistonapi/piston.py
pistonapi-1.0.1.dist-info/METADATA
pistonapi-1.0.1.dist-info/WHEEL
pistonapi-1.0.1.dist-info/top_level.txt
pistonapi-1.0.1.dist-info/RECORD
