Metadata-Version: 2.1
Name: pistonapi
Version: 1.0.1
Summary: Unofficial Piston API Wrapper for Python
Home-page: https://github.com/justaprudev/pistonapi
Author: Priyam Kalra
Author-email: justaprudev@gmail.com
License: UNKNOWN
Platform: UNKNOWN
